{
    "html_attributions": [],
    "next_page_token": "some token",
    "results": [
      {
        "username": "Shrey",
        "start": "fat",
        "day": 1,
        "image":"https://cdn.quotesgram.com/img/59/69/1147595935-36fa4761-1ded-494b-a56e-b8258ce5cae2weird-people-fat-guy-eating-huge-ha.jpg",
        "comments": ["OMG FAT TO FIT JOURNEY", "congrats!", "lets go"],
        "likes": 79,
        "friends": ["mihika", "sibi", "shreyus"],
        "buddies": ["nilan", "sid", "sravan"]
      },
      {
        "username": "GigaChad",
        "start": "fit",
        "day": 99,
        "image":"https://th.bing.com/th/id/R.5dcbd67f357064ca964064d7aeaba14c?rik=J1BnxiQyOcIT1Q&pid=ImgRaw&r=0",
        "comments": ["giga chad", "insane", "fit sheesh"],
        "likes": 999,
        "friends": ["shrey", "god", "jim"],
        "buddies": ["protien", "muskelies", "shrey"]
      }
    ],
    "status": "OK"
  }